<annotation>
	<folder>images</folder>
	<filename>089_0010.jpg</filename>
	<path>/media/biscuit/HARDDRIVE/goose_dataset/unified/images/train/089_0010.jpg</path>
	<source>
		<database>Unknown</database>
	</source>
	<size>
		<width>2272</width>
		<height>1704</height>
		<depth>3</depth>
	</size>
	<segmented>0</segmented>
	<object>
		<name>goose</name>
		<pose>Unspecified</pose>
		<truncated>0</truncated>
		<difficult>0</difficult>
		<bndbox>
			<xmin>866</xmin>
			<ymin>219</ymin>
			<xmax>1584</xmax>
			<ymax>1534</ymax>
		</bndbox>
	</object>
	<object>
		<name>goose</name>
		<pose>Unspecified</pose>
		<truncated>1</truncated>
		<difficult>0</difficult>
		<bndbox>
			<xmin>1</xmin>
			<ymin>454</ymin>
			<xmax>510</xmax>
			<ymax>971</ymax>
		</bndbox>
	</object>
</annotation>
