<annotation>
	<folder>train</folder>
	<filename>g83.jpg</filename>
	<path>/media/biscuit/HARDDRIVE/goose_dataset/unified/images/train/g83.jpg</path>
	<source>
		<database>Unknown</database>
	</source>
	<size>
		<width>600</width>
		<height>371</height>
		<depth>3</depth>
	</size>
	<segmented>0</segmented>
	<object>
		<name>goose</name>
		<pose>Unspecified</pose>
		<truncated>0</truncated>
		<difficult>0</difficult>
		<bndbox>
			<xmin>32</xmin>
			<ymin>157</ymin>
			<xmax>120</xmax>
			<ymax>284</ymax>
		</bndbox>
	</object>
	<object>
		<name>goose</name>
		<pose>Unspecified</pose>
		<truncated>0</truncated>
		<difficult>0</difficult>
		<bndbox>
			<xmin>196</xmin>
			<ymin>101</ymin>
			<xmax>308</xmax>
			<ymax>332</ymax>
		</bndbox>
	</object>
	<object>
		<name>goose</name>
		<pose>Unspecified</pose>
		<truncated>1</truncated>
		<difficult>0</difficult>
		<bndbox>
			<xmin>502</xmin>
			<ymin>163</ymin>
			<xmax>600</xmax>
			<ymax>324</ymax>
		</bndbox>
	</object>
</annotation>
